contact_profile_local/__init__.py
contact_profile_local/contact_profiles_local.py
contact_profile_local/contact_profiles_local_constants.py
contact_profile_local-0.0.34.dist-info/METADATA
contact_profile_local-0.0.34.dist-info/WHEEL
contact_profile_local-0.0.34.dist-info/top_level.txt
contact_profile_local-0.0.34.dist-info/RECORD
