Metadata-Version: 2.4
Name: contact-profile-local
Version: 0.0.34
Summary: PyPI Package for Circles contact-profile-local Python
Home-page: https://github.com/circles-zone/contact-profile-local-python-package
Author: Circles
Author-email: info@circlez.ai
Classifier: Programming Language :: Python :: 3
Classifier: License :: Other/Proprietary License
Classifier: Operating System :: OS Independent
Requires-Dist: logger-local>=0.0.135
Requires-Dist: database-mysql-local>=0.0.290
Requires-Dist: contact-persons-local>=0.0.19
Requires-Dist: language-remote>=0.0.20
Requires-Dist: profile-local>=0.0.79
Requires-Dist: user-context-remote>=0.0.75
Dynamic: author
Dynamic: author-email
Dynamic: classifier
Dynamic: description
Dynamic: description-content-type
Dynamic: home-page
Dynamic: requires-dist
Dynamic: summary
